LICENSE
README.md
pyproject.toml
setup.py
spdb/__init__.py
spdb/db.py
spdb/db_utils.py
spdb/generator_utils.py
spdb/loggers.py
spdb/otp.py
spdb/quotes.py
spdb/restr.py
spdb/text_validator.py
spdb/token_generator.py
spdb/utils.py
spdb.egg-info/PKG-INFO
spdb.egg-info/SOURCES.txt
spdb.egg-info/dependency_links.txt
spdb.egg-info/not-zip-safe
spdb.egg-info/requires.txt
spdb.egg-info/top_level.txt