Metadata-Version: 2.1
Name: spdb
Version: 2.1.4
Summary: SPDB - Sassy Python DB
Author-email: Mrybs <mrybs2@gmail.com>
Project-URL: Homepage, https://github.com/mrybs/spdb
Project-URL: Bug Tracker, https://github.com/mrybs/spdb/issues
Classifier: Programming Language :: Python :: 3
Classifier: License :: OSI Approved :: MIT License
Classifier: Operating System :: OS Independent
Requires-Python: >=3.7
License-File: LICENSE
